furigrego/__init__.py
furigrego/add_furigana.py
furigrego/checking.py
furigrego/cli.py
furigrego/constants.py
furigrego/converter.py
furigrego/furigrego.egg-info/dependency_links.txt
furigrego/furigrego.egg-info/PKG-INFO
furigrego/furigrego.egg-info/requires.txt
furigrego/furigrego.egg-info/SOURCES.txt
furigrego/furigrego.egg-info/top_level.txt
furigrego/process_ebook.py
furigrego-1.0.5.dist-info/entry_points.txt
furigrego-1.0.5.dist-info/METADATA
furigrego-1.0.5.dist-info/WHEEL
furigrego-1.0.5.dist-info/RECORD
